soundsliceapi.py
soundsliceapi-1.1.dist-info/LICENSE
soundsliceapi-1.1.dist-info/WHEEL
soundsliceapi-1.1.dist-info/METADATA
soundsliceapi-1.1.dist-info/RECORD
