Metadata-Version: 2.1
Name: soundsliceapi
Version: 1.1
Summary: The official Python library for Soundslice's data API.
Home-page: https://github.com/soundslice/soundsliceapi/
Author: Soundslice
Author-email: feedback@soundslice.com
Classifier: License :: OSI Approved :: MIT License
Requires-Dist: requests >=2.25
